virtualenv_multiver/__init__.py
virtualenv_multiver/config.py
virtualenv_multiver/main.py
virtualenv_multiver/pydo.py
virtualenv_multiver/utils.py
virtualenv_multiver-3.0.dist-info/licenses/AUTHORS
virtualenv_multiver-3.0.dist-info/METADATA
virtualenv_multiver-3.0.dist-info/WHEEL
virtualenv_multiver-3.0.dist-info/entry_points.txt
virtualenv_multiver-3.0.dist-info/top_level.txt
virtualenv_multiver-3.0.dist-info/RECORD
