Metadata-Version: 2.4
Name: virtualenv-multiver
Version: 3.0
Summary: Install a virtualenv containing many Python versions.
Author-email: "Beanbag, Inc." <questions@beanbaginc.com>
License: MIT
Project-URL: Homepage, https://github.com/beanbaginc/virtualenv-multiver
Project-URL: Documentation, https://github.com/beanbaginc/virtualenv-multiver
Project-URL: Repository, https://github.com/beanbaginc/virtualenv-multiver
Classifier: Development Status :: 5 - Production/Stable
Classifier: Environment :: Other Environment
Classifier: Intended Audience :: Developers
Classifier: License :: OSI Approved :: MIT License
Classifier: Operating System :: OS Independent
Classifier: Programming Language :: Python
Classifier: Programming Language :: Python :: 3
Classifier: Programming Language :: Python :: 3.8
Classifier: Programming Language :: Python :: 3.9
Classifier: Programming Language :: Python :: 3.10
Classifier: Programming Language :: Python :: 3.11
Classifier: Programming Language :: Python :: 3.12
Classifier: Programming Language :: Python :: 3.13
Classifier: Programming Language :: Python :: 3.14
Classifier: Topic :: Software Development
Classifier: Topic :: Software Development :: Testing
Requires-Python: >=3.8
License-File: AUTHORS
Requires-Dist: toml; python_version < "3.11"
Requires-Dist: virtualenv
Dynamic: license-file
